twder/__init__.py
twder/a.py
twder/api.py
twder-0.2.2.dist-info/LICENSE
twder-0.2.2.dist-info/METADATA
twder-0.2.2.dist-info/WHEEL
twder-0.2.2.dist-info/top_level.txt
twder-0.2.2.dist-info/RECORD
