Metadata-Version: 2.1
Name: twder
Version: 0.2.2
Summary: 新台幣匯率擷取 (New Taiwan Dollar Exchange Rate)
Home-page: https://github.com/jimms/twder
Author: Jimms Hsieh
Author-email: jimms.hsieh@gmail.com
License: MIT
Keywords: NTD TWD 匯率 exchange rate
Platform: UNKNOWN
Classifier: Development Status :: 3 - Alpha
Classifier: Environment :: Console
Classifier: Intended Audience :: Financial and Insurance Industry
Classifier: Intended Audience :: Developers
Classifier: License :: OSI Approved :: MIT License
Classifier: Natural Language :: Chinese (Traditional)
Classifier: Programming Language :: Python
Classifier: Programming Language :: Python :: 3.5
Classifier: Topic :: Office/Business :: Financial :: Investment
Requires-Dist: lxml
